README.md
setup.py
defcollect/__init__.py
defcollect.egg-info/PKG-INFO
defcollect.egg-info/SOURCES.txt
defcollect.egg-info/dependency_links.txt
defcollect.egg-info/not-zip-safe
defcollect.egg-info/top_level.txt