Metadata-Version: 1.0
Name: defcollect
Version: 0.1
Summary: Create types and form definitions for data collection
Home-page: http://github.com/dhontecillas/defcollect
Author: David Hontecillas
Author-email: dhontecillas@gmail.com
License: MIT
Platform: UNKNOWN
